TimeShow/__init__.py
TimeShow/checkPythonVersion.py
TimeShow/timeShow.py
TimeShow-2023.1.9.dist-info/LICENSE
TimeShow-2023.1.9.dist-info/METADATA
TimeShow-2023.1.9.dist-info/WHEEL
TimeShow-2023.1.9.dist-info/top_level.txt
TimeShow-2023.1.9.dist-info/RECORD
